librosax/__init__.py
librosax/_cache.py
librosax/_typing.py
librosax/version.py
librosax/core/__init__.py
librosax/core/convert.py
librosax/core/intervals.py
librosax/core/notation.py
librosax/core/spectrum.py
librosax/feature/__init__.py
librosax/feature/spectral.py
librosax/layers/__init__.py
librosax/layers/core.py
librosax/util/__init__.py
librosax/util/decorators.py
librosax/util/exceptions.py
librosax/util/files.py
librosax-0.1.1.dist-info/licenses/LICENSE
librosax-0.1.1.dist-info/METADATA
librosax-0.1.1.dist-info/WHEEL
librosax-0.1.1.dist-info/top_level.txt
librosax-0.1.1.dist-info/RECORD
