Metadata-Version: 2.4
Name: librosax
Version: 0.1.1
Summary: A JAX implementation of librosa, TorchLibrosa, and nnAudio
Home-page: https://github.com/DBraun/librosax
Author: David Braun
Author-email: David Braun <braun@ccrma.stanford.edu>
License: ISC
Project-URL: Homepage, https://github.com/DBraun/librosax
Project-URL: Issues, https://github.com/DBraun/librosax/issues
Keywords: audio,machine learning,jax
Classifier: Programming Language :: Python :: 3
Classifier: License :: OSI Approved :: ISC License (ISCL)
Classifier: Operating System :: OS Independent
Requires-Python: >=3.11
License-File: LICENSE
Requires-Dist: einops>=0.8.1
Requires-Dist: flax>=0.12.0
Requires-Dist: jax>=0.8.0
Requires-Dist: librosa>=0.10.1
Requires-Dist: numpy>=2.1.3
Requires-Dist: scipy>=1.16.2
Provides-Extra: dev
Requires-Dist: pytest; extra == "dev"
Requires-Dist: pytest-cov; extra == "dev"
Requires-Dist: torch; extra == "dev"
Requires-Dist: torchlibrosa; extra == "dev"
Provides-Extra: docs
Requires-Dist: sphinx>=4.0; extra == "docs"
Requires-Dist: furo; extra == "docs"
Requires-Dist: m2r2; extra == "docs"
Requires-Dist: sphinx-autobuild; extra == "docs"
Dynamic: license-file
